scistag/__init__.py
scistag/__main__.py
scistag/addons/__init__.py
scistag/addons/__main__.py
scistag/addons/addon_manager.py
scistag/cli/cli_demo.py
scistag/cli/main_cli.py
scistag/common/__init__.py
scistag/common/cache.py
scistag/common/cache_ref.py
scistag/common/classes.py
scistag/common/component.py
scistag/common/config_stag.py
scistag/common/configuration.py
scistag/common/disk_cache.py
scistag/common/env.py
scistag/common/essential_data.py
scistag/common/iter_helper.py
scistag/common/list_helper.py
scistag/common/mt/__init__.py
scistag/common/mt/managed_thread.py
scistag/common/mt/stag_lock.py
scistag/common/mt/task_thread.py
scistag/common/observer.py
scistag/common/stag_app.py
scistag/common/sytem_info.py
scistag/common/test_data.py
scistag/common/time/__init__.py
scistag/common/trees/__init__.py
scistag/common/trees/text_tree.py
scistag/common/trees/tree_node.py
scistag/cutestag/__init__.py
scistag/cutestag/browser/__init__.py
scistag/cutestag/browser/browser_app.py
scistag/data/.gitignore
scistag/data/__init__.py
scistag/data/addon_packages.json
scistag/data/scistag_essentials.zip
scistag/datastag/__init__.py
scistag/datastag/data_stag_command_handler.py
scistag/datastag/data_stag_common.py
scistag/datastag/data_stag_connection.py
scistag/datastag/data_stag_element.py
scistag/datastag/data_stag_list.py
scistag/datastag/data_stag_vault.py
scistag/datastag/flask/__init__.py
scistag/datastag/flask/data_stag_blueprint.py
scistag/emojistag/__init__.py
scistag/emojistag/emoji_db.py
scistag/emojistag/emoji_definitions.py
scistag/emojistag/emoji_info.py
scistag/emojistag/emoji_renderer.py
scistag/examples/__init__.py
scistag/examples/imagestag/__init__.py
scistag/examples/imagestag/filter_overview.py
scistag/examples/imagestag/image.py
scistag/examples/imagestag/image_cv2.py
scistag/examples/imagestag/image_filter.py
scistag/examples/mediastag/__init__.py
scistag/examples/mediastag/video.py
scistag/examples/mediastag/webcam.py
scistag-0.9.0.dist-info/LICENSE.md
scistag-0.9.0.dist-info/METADATA
scistag-0.9.0.dist-info/WHEEL
scistag-0.9.0.dist-info/RECORD
