Metadata-Version: 2.1
Name: scistag
Version: 0.9.0
Summary: A stack of helpful libraries & applications for the rapid development of data driven solutions.
Home-page: https://github.com/scistag/scistag
License: MIT
Keywords: Data Science,Data Engineering,Data Visualization,Logging,Computer Vision
Author: Michael Ikemann
Requires-Python: >=3.9,<3.13
Classifier: Intended Audience :: Developers
Classifier: License :: OSI Approved :: MIT License
Classifier: Operating System :: OS Independent
Classifier: Programming Language :: Python
Classifier: Programming Language :: Python :: 3
Classifier: Programming Language :: Python :: 3.9
Classifier: Programming Language :: Python :: 3.10
Classifier: Programming Language :: Python :: 3.11
Classifier: Programming Language :: Python :: 3.12
Classifier: Topic :: Software Development :: Libraries :: Python Modules
Provides-Extra: azure
Provides-Extra: common
Provides-Extra: cutestag
Provides-Extra: datastag
Provides-Extra: flask
Provides-Extra: full
Provides-Extra: jupyter
Provides-Extra: kivy
Provides-Extra: logstag
Provides-Extra: moviepy
Provides-Extra: opencv
Provides-Extra: opencvcon
Provides-Extra: svg
Provides-Extra: webstag
Requires-Dist: CairoSVG (>=2.5.2,<3.0.0) ; extra == "svg" or extra == "common" or extra == "full"
Requires-Dist: Flask (>=2.1.2,<3.0.0) ; extra == "flask" or extra == "common" or extra == "full"
Requires-Dist: Jinja2 (>=3.1.2,<4.0.0) ; extra == "logstag" or extra == "common" or extra == "full"
Requires-Dist: Markdown (>=3.5.2,<4.0.0) ; extra == "logstag" or extra == "common" or extra == "full"
Requires-Dist: PySide6-Addons (==6.4.1) ; (python_version < "3.12") and (extra == "cutestag" or extra == "full")
Requires-Dist: azure-storage-blob (>=12.13.1,<13.0.0) ; extra == "azure" or extra == "full"
Requires-Dist: chartstag (==0.8.2) ; extra == "common" or extra == "full"
Requires-Dist: filetype (>=1.1.0,<2.0.0) ; extra == "logstag" or extra == "common" or extra == "full"
Requires-Dist: gunicorn (>=20.1.0,<21.0.0) ; extra == "flask" or extra == "common" or extra == "full"
Requires-Dist: imgkit (==1.2.2) ; extra == "moviepy" or extra == "common" or extra == "full"
Requires-Dist: jupyter (>=1.0.0,<2.0.0) ; extra == "jupyter" or extra == "full"
Requires-Dist: jupyterlab (>=3.4.7) ; extra == "jupyter" or extra == "full"
Requires-Dist: kivy (>=2.1.0,<3.0.0) ; extra == "kivy" or extra == "full"
Requires-Dist: matplotlib (>=3.5.2,<4.0.0) ; extra == "logstag" or extra == "common" or extra == "common" or extra == "full" or extra == "full"
Requires-Dist: mkdocs (>=1.4.3,<2.0.0) ; extra == "full"
Requires-Dist: moviepy (>=1.0.3,<2.0.0) ; extra == "moviepy" or extra == "common" or extra == "full"
Requires-Dist: numpy (>=1.23.5,<2.0.0)
Requires-Dist: opencv-contrib-python (>=4.7.0.72,<5.0.0.0) ; extra == "opencvcon" or extra == "full"
Requires-Dist: opencv-python (>=4.7.0.72,<5.0.0.0) ; extra == "opencv"
Requires-Dist: pandas (>=1.4.2)
Requires-Dist: pillow (>=9.2.0,<10.0.0)
Requires-Dist: pydantic (>=2.5.3,<3.0.0)
Requires-Dist: requests (>=2.27.1,<3.0.0) ; extra == "webstag" or extra == "common" or extra == "full"
Requires-Dist: shiboken6 (==6.4.1) ; (python_version < "3.12") and (extra == "cutestag")
Requires-Dist: tabulate (>=0.9.0,<0.10.0) ; extra == "logstag" or extra == "common" or extra == "full"
Project-URL: Documentation, https://scistag.readthedocs.io
Project-URL: Repository, https://github.com/scistag/scistag
